jambot_client/__init__.py
jambot_client/clients/__init__.py
jambot_client/clients/base_client.py
jambot_client/clients/bridge/__init__.py
jambot_client/clients/bridge/client.py
jambot_client-0.1.0.dist-info/WHEEL
jambot_client-0.1.0.dist-info/METADATA
jambot_client-0.1.0.dist-info/RECORD
